lossy_mpi/__init__.py
lossy_mpi/comms.py
lossy_mpi/pool.py
lossy_mpi/util.py
lossy_mpi-0.1.1.dist-info/METADATA
lossy_mpi-0.1.1.dist-info/WHEEL
lossy_mpi-0.1.1.dist-info/RECORD
